openmoji_dist
