Metadata-Version: 2.4
Name: openmoji-dist
Version: 16.0.0
Summary: Openmoji files
Home-page: https://codeberg.org/Joshix/py-openmoji
License: CC-BY-SA-4.0
Platform: OS Independent
Classifier: Development Status :: 5 - Production/Stable
Classifier: Operating System :: OS Independent
Classifier: Programming Language :: Python :: 3 :: Only
Classifier: Typing :: Typed
Dynamic: classifier
Dynamic: description
Dynamic: home-page
Dynamic: license
Dynamic: platform
Dynamic: summary
